{
  "zones": [
    {
      "id": 1,
      "name": "Зона Петроградка",
      "street": "Газовая 1А",
      "fillColor": [
        0.2,
        0.8,
        0.2,
        0.4
      ],
      "points": [
        {
          "lng": 30.2945629,
          "lat": 59.9642681
        },
        {
          "lng": 30.2947205,
          "lat": 59.9642051
        },
        {
          "lng": 30.2951774,
          "lat": 59.9646558
        },
        {
          "lng": 30.2948996,
          "lat": 59.9646797
        },
        {
          "lng": 30.2948864,
          "lat": 59.9645691
        },
        {
          "lng": 30.2945629,
          "lat": 59.9642681
        }
      ]
    },
    {
      "id": 2,
      "name": "Зона Центральный район",
      "street": "Греческий проспект 10",
      "fillColor": [
        0.2,
        0.8,
        0.2,
        0.4
      ],
      "points": [
        {
          "lng": 30.3677225,
          "lat": 59.9384047
        },
        {
          "lng": 30.3680579,
          "lat": 59.9383703
        },
        {
          "lng": 30.3683367,
          "lat": 59.9391172
        },
        {
          "lng": 30.3698237,
          "lat": 59.9389714
        },
        {
          "lng": 30.3699288,
          "lat": 59.9391314
        },
        {
          "lng": 30.3685145,
          "lat": 59.9392629
        },
        {
          "lng": 30.3686074,
          "lat": 59.9394876
        },
        {
          "lng": 30.3680498,
          "lat": 59.9395443
        },
        {
          "lng": 30.3679124,
          "lat": 59.9391617
        },
        {
          "lng": 30.3680215,
          "lat": 59.9391354
        },
        {
          "lng": 30.3677225,
          "lat": 59.9384047
        }
      ]
    },
    {
      "id": 3,
      "name": "Зона Центральный район",
      "street": "Парадная 7",
      "fillColor": [
        0.2,
        0.8,
        0.2,
        0.4
      ],
      "points": [
        {
          "lng": 30.37005,
          "lat": 59.9410881
        },
        {
          "lng": 30.3702641,
          "lat": 59.943204
        },
        {
          "lng": 30.3703484,
          "lat": 59.9432054
        },
        {
          "lng": 30.3703149,
          "lat": 59.9428074
        },
        {
          "lng": 30.3708463,
          "lat": 59.9427962
        },
        {
          "lng": 30.3708285,
          "lat": 59.9426687
        },
        {
          "lng": 30.3703372,
          "lat": 59.9426832
        },
        {
          "lng": 30.3702837,
          "lat": 59.9422392
        },
        {
          "lng": 30.3707771,
          "lat": 59.9422247
        },
        {
          "lng": 30.3707654,
          "lat": 59.9421028
        },
        {
          "lng": 30.3702854,
          "lat": 59.9421139
        },
        {
          "lng": 30.370237,
          "lat": 59.9416806
        },
        {
          "lng": 30.3707014,
          "lat": 59.9416705
        },
        {
          "lng": 30.3706791,
          "lat": 59.9415386
        },
        {
          "lng": 30.3702102,
          "lat": 59.9415553
        },
        {
          "lng": 30.3701671,
          "lat": 59.9411036
        },
        {
          "lng": 30.3706539,
          "lat": 59.941098
        },
        {
          "lng": 30.3706293,
          "lat": 59.9409828
        },
        {
          "lng": 30.3702006,
          "lat": 59.9410029
        },
        {
          "lng": 30.3700399,
          "lat": 59.941032
        },
        {
          "lng": 30.37005,
          "lat": 59.9410881
        }
      ]
    }
  ]
}